MainFileHostUtils/__init__.py
MainFileHostUtils/client/__init__.py
MainFileHostUtils/server/__init__.py
mainfilehostutils-0.0.0.dist-info/METADATA
mainfilehostutils-0.0.0.dist-info/WHEEL
mainfilehostutils-0.0.0.dist-info/entry_points.txt
mainfilehostutils-0.0.0.dist-info/RECORD
